{
  "success": true,
  "data": [{
    "loginName": 1,
    "1": "wl2",
    "2": "张二",
    "3": null,
    "4": "管理组",
    "5": "管理员",
    "6": "女",
    "7": 1,
    "8": 2 ,
    "9": "女",
    "10": 1,
    "11":"aaa"
  },{
    "loginName": 2,
    "1": "wl2",
    "2": "张二",
    "3": null,
    "4": "管理组",
    "5": "管理员",
    "6": "女",
    "7": 1,
    "8": 2 ,
    "9": "女",
    "10": 1,
    "11":"aaa"
  },{
    "loginName": 3,
    "1": "wl2",
    "2": "张二",
    "3": null,
    "4": "管理组",
    "5": "管理员",
    "6": "女",
    "7": 1,
    "8": 2 ,
    "9": "女",
    "10": 1,
    "11":"aaa"
  }
    ]
}